[
  {
    "code": "2659",
    "cmp": "楠梓校區",
    "dgr": "日間部博士",
    "unt": "航運管理系博士班",
    "className": "航管系博班一甲",
    "foreverID": "331A00002",
    "courseName": "專題研討(二)",
    "hours": "2.0",
    "units": "2.0",
    "required": "必修",
    "instructors": "楊清喬,趙清成",
    "position": "2203實驗室",
    "people": "5",
    "maxpeople": "30",
    "time": "(一)3-4",
    "english": "否",
    "remote": "否",
    "href": [
      "108",
      "2",
      "UO081811,01680.01"
    ],
    "note": "限原有繳費參加泰國參訪者選修,否經發現一律由系辦退選"
  },
  {
    "code": "2660",
    "cmp": "楠梓校區",
    "dgr": "日間部博士",
    "unt": "航運管理系博士班",
    "className": "航管系博班一甲",
    "foreverID": "331A10007",
    "courseName": "評估方法",
    "hours": "3.0",
    "units": "3.0",
    "required": "選修",
    "instructors": "戴輝煌",
    "position": "2203實驗室",
    "people": "13",
    "maxpeople": "30",
    "time": "(五)5-7",
    "english": "否",
    "remote": "否",
    "href": [
      "108",
      "2",
      "UO081811,06429.01"
    ],
    "note": ""
  },
  {
    "code": "2661",
    "cmp": "楠梓校區",
    "dgr": "日間部博士",
    "unt": "航運管理系博士班",
    "className": "航管系博班一甲",
    "foreverID": "331A10036",
    "courseName": "航港經營策略專論",
    "hours": "3.0",
    "units": "3.0",
    "required": "選修",
    "instructors": "楊鈺池",
    "position": "2203實驗室",
    "people": "5",
    "maxpeople": "30",
    "time": "(二)5-7",
    "english": "否",
    "remote": "否",
    "href": [
      "108",
      "2",
      "UO081811,30014.01"
    ],
    "note": ""
  },
  {
    "code": "2663",
    "cmp": "楠梓校區",
    "dgr": "日間部博士",
    "unt": "航運管理系博士班",
    "className": "航管系博班一甲",
    "foreverID": "331A10008",
    "courseName": "物流策略專論",
    "hours": "3.0",
    "units": "3.0",
    "required": "選修",
    "instructors": "楊清喬",
    "position": "2202教室",
    "people": "5",
    "maxpeople": "15",
    "time": "(四)5-7",
    "english": "是",
    "remote": "否",
    "href": [
      "108",
      "2",
      "UO081811,B0405.01"
    ],
    "note": "全英授課"
  },
  {
    "code": "2664",
    "cmp": "楠梓校區",
    "dgr": "日間部博士",
    "unt": "航運管理系博士班",
    "className": "航管系博班一甲",
    "foreverID": "331A10033",
    "courseName": "海上保險專論",
    "hours": "3.0",
    "units": "3.0",
    "required": "選修",
    "instructors": "曾文瑞",
    "position": "2203實驗室",
    "people": "8",
    "maxpeople": "30",
    "time": "(四)2-4",
    "english": "否",
    "remote": "否",
    "href": [
      "108",
      "2",
      "UO081811,B0598.01"
    ],
    "note": ""
  },
  {
    "code": "2665",
    "cmp": "楠梓校區",
    "dgr": "日間部博士",
    "unt": "航運管理系博士班",
    "className": "航管系博班一甲",
    "foreverID": "331A10016",
    "courseName": "國際運輸產業海外專題",
    "hours": "3.0",
    "units": "3.0",
    "required": "選修",
    "instructors": "于惠蓉",
    "position": "2203實驗室",
    "people": "11",
    "maxpeople": "30",
    "time": "(一)2(四)8-9",
    "english": "否",
    "remote": "否",
    "href": [
      "108",
      "2",
      "UO081811,B1257.01"
    ],
    "note": "限至越南進行參訪者選修"
  },
  {
    "code": "2666",
    "cmp": "楠梓校區",
    "dgr": "日間部博士",
    "unt": "航運管理系博士班",
    "className": "航管系博班一甲",
    "foreverID": "331A10012",
    "courseName": "航運業服務品質管理",
    "hours": "3.0",
    "units": "3.0",
    "required": "選修",
    "instructors": "許文楷",
    "position": "2203實驗室",
    "people": "6",
    "maxpeople": "30",
    "time": "(二)2-4",
    "english": "是",
    "remote": "否",
    "href": [
      "108",
      "2",
      "UO081811,B2353.01"
    ],
    "note": "全英授課"
  },
  {
    "code": "2660",
    "cmp": "楠梓校區",
    "dgr": "日間部博士",
    "unt": "航運管理系博士班",
    "className": "航管系博班二甲",
    "foreverID": "331A10007",
    "courseName": "評估方法",
    "hours": "3.0",
    "units": "3.0",
    "required": "選修",
    "instructors": "戴輝煌",
    "position": "2203實驗室",
    "people": "13",
    "maxpeople": "30",
    "time": "(五)5-7",
    "english": "否",
    "remote": "否",
    "href": [
      "108",
      "2",
      "UO081811,06429.01"
    ],
    "note": ""
  },
  {
    "code": "2661",
    "cmp": "楠梓校區",
    "dgr": "日間部博士",
    "unt": "航運管理系博士班",
    "className": "航管系博班二甲",
    "foreverID": "331A10036",
    "courseName": "航港經營策略專論",
    "hours": "3.0",
    "units": "3.0",
    "required": "選修",
    "instructors": "楊鈺池",
    "position": "2203實驗室",
    "people": "5",
    "maxpeople": "30",
    "time": "(二)5-7",
    "english": "否",
    "remote": "否",
    "href": [
      "108",
      "2",
      "UO081811,30014.01"
    ],
    "note": ""
  },
  {
    "code": "2663",
    "cmp": "楠梓校區",
    "dgr": "日間部博士",
    "unt": "航運管理系博士班",
    "className": "航管系博班二甲",
    "foreverID": "331A10008",
    "courseName": "物流策略專論",
    "hours": "3.0",
    "units": "3.0",
    "required": "選修",
    "instructors": "楊清喬",
    "position": "2202教室",
    "people": "5",
    "maxpeople": "15",
    "time": "(四)5-7",
    "english": "是",
    "remote": "否",
    "href": [
      "108",
      "2",
      "UO081811,B0405.01"
    ],
    "note": "全英授課"
  },
  {
    "code": "2664",
    "cmp": "楠梓校區",
    "dgr": "日間部博士",
    "unt": "航運管理系博士班",
    "className": "航管系博班二甲",
    "foreverID": "331A10033",
    "courseName": "海上保險專論",
    "hours": "3.0",
    "units": "3.0",
    "required": "選修",
    "instructors": "曾文瑞",
    "position": "2203實驗室",
    "people": "8",
    "maxpeople": "30",
    "time": "(四)2-4",
    "english": "否",
    "remote": "否",
    "href": [
      "108",
      "2",
      "UO081811,B0598.01"
    ],
    "note": ""
  },
  {
    "code": "2665",
    "cmp": "楠梓校區",
    "dgr": "日間部博士",
    "unt": "航運管理系博士班",
    "className": "航管系博班二甲",
    "foreverID": "331A10016",
    "courseName": "國際運輸產業海外專題",
    "hours": "3.0",
    "units": "3.0",
    "required": "選修",
    "instructors": "于惠蓉",
    "position": "2203實驗室",
    "people": "11",
    "maxpeople": "30",
    "time": "(一)2(四)8-9",
    "english": "否",
    "remote": "否",
    "href": [
      "108",
      "2",
      "UO081811,B1257.01"
    ],
    "note": "限至越南進行參訪者選修"
  },
  {
    "code": "2666",
    "cmp": "楠梓校區",
    "dgr": "日間部博士",
    "unt": "航運管理系博士班",
    "className": "航管系博班二甲",
    "foreverID": "331A10012",
    "courseName": "航運業服務品質管理",
    "hours": "3.0",
    "units": "3.0",
    "required": "選修",
    "instructors": "許文楷",
    "position": "2203實驗室",
    "people": "6",
    "maxpeople": "30",
    "time": "(二)2-4",
    "english": "是",
    "remote": "否",
    "href": [
      "108",
      "2",
      "UO081811,B2353.01"
    ],
    "note": "全英授課"
  }
]