[
  {
    "code": "1271",
    "cmp": "第一校區",
    "dgr": "碩士在職專班",
    "unt": "運籌管理系企業管理碩士專班",
    "className": "運籌企專班一甲",
    "foreverID": "136H00006",
    "courseName": "企業研究方法",
    "hours": "3.0",
    "units": "3.0",
    "required": "必修",
    "instructors": "",
    "position": "",
    "people": "0",
    "maxpeople": "20",
    "time": "",
    "english": "否",
    "remote": "否",
    "href": [
      "93",
      "2",
      "UN262711,F1353.01"
    ],
    "note": ""
  },
  {
    "code": "1272",
    "cmp": "第一校區",
    "dgr": "碩士在職專班",
    "unt": "運籌管理系企業管理碩士專班",
    "className": "運籌企專班一甲",
    "foreverID": "136H10049",
    "courseName": "智慧財產權管理",
    "hours": "3.0",
    "units": "3.0",
    "required": "選修",
    "instructors": "",
    "position": "",
    "people": "0",
    "maxpeople": "20",
    "time": "",
    "english": "否",
    "remote": "否",
    "href": [
      "93",
      "2",
      "UN262711,F2769.01"
    ],
    "note": ""
  },
  {
    "code": "1273",
    "cmp": "第一校區",
    "dgr": "碩士在職專班",
    "unt": "運籌管理系企業管理碩士專班",
    "className": "運籌企專班一甲",
    "foreverID": "136H10016",
    "courseName": "創業投資管理",
    "hours": "3.0",
    "units": "3.0",
    "required": "選修",
    "instructors": "",
    "position": "",
    "people": "0",
    "maxpeople": "20",
    "time": "",
    "english": "否",
    "remote": "否",
    "href": [
      "93",
      "2",
      "UN262711,F1434.01"
    ],
    "note": ""
  },
  {
    "code": "1274",
    "cmp": "第一校區",
    "dgr": "碩士在職專班",
    "unt": "運籌管理系企業管理碩士專班",
    "className": "運籌企專班一甲",
    "foreverID": "136H10037",
    "courseName": "策略管理專題",
    "hours": "3.0",
    "units": "3.0",
    "required": "選修",
    "instructors": "",
    "position": "",
    "people": "0",
    "maxpeople": "20",
    "time": "",
    "english": "否",
    "remote": "否",
    "href": [
      "93",
      "2",
      "UN262711,06324.01"
    ],
    "note": ""
  }
]