[
  {
    "code": "1416",
    "cmp": "楠梓校區",
    "dgr": "日間部四技",
    "unt": "自動化學程",
    "className": "日自動化學程",
    "foreverID": "350C10160",
    "courseName": "油氣壓學",
    "hours": "3.0",
    "units": "3.0",
    "required": "選修",
    "instructors": "陳紹榮",
    "position": "5102教室",
    "people": "61",
    "maxpeople": "60",
    "time": "(三)1-2,8",
    "english": "否",
    "remote": "否",
    "href": [
      "101",
      "2",
      "GF011400,09859.01"
    ],
    "note": "二年級以上學生才得選修此課程，修讀資格請參閱學程修讀辦法"
  }
]