[
  {
    "code": "0052",
    "cmp": "建工校區",
    "dgr": "日間部四技",
    "unt": "電子工程系[建工|燕巢校區 ]",
    "className": "四子三甲",
    "foreverID": "222C10566",
    "courseName": "暑期實習",
    "hours": "2.0",
    "units": "2.0",
    "required": "選修",
    "instructors": "李財福",
    "position": "教室未定",
    "people": "6",
    "maxpeople": "55",
    "time": "",
    "english": "否",
    "remote": "否",
    "href": [
      "107",
      "4",
      "UE291431,09635.01"
    ],
    "note": ""
  },
  {
    "code": "0052",
    "cmp": "建工校區",
    "dgr": "日間部四技",
    "unt": "電子工程系[建工|燕巢校區 ]",
    "className": "四子三乙",
    "foreverID": "222C10566",
    "courseName": "暑期實習",
    "hours": "2.0",
    "units": "2.0",
    "required": "選修",
    "instructors": "李財福",
    "position": "教室未定",
    "people": "6",
    "maxpeople": "55",
    "time": "",
    "english": "否",
    "remote": "否",
    "href": [
      "107",
      "4",
      "UE291431,09635.01"
    ],
    "note": ""
  },
  {
    "code": "0052",
    "cmp": "建工校區",
    "dgr": "日間部四技",
    "unt": "電子工程系[建工|燕巢校區 ]",
    "className": "四子三丙",
    "foreverID": "222C10566",
    "courseName": "暑期實習",
    "hours": "2.0",
    "units": "2.0",
    "required": "選修",
    "instructors": "李財福",
    "position": "教室未定",
    "people": "6",
    "maxpeople": "55",
    "time": "",
    "english": "否",
    "remote": "否",
    "href": [
      "107",
      "4",
      "UE291431,09635.01"
    ],
    "note": ""
  },
  {
    "code": "0154",
    "cmp": "建工校區",
    "dgr": "日間部四技",
    "unt": "電子工程系[建工|燕巢校區 ]",
    "className": "四子四甲",
    "foreverID": "222C10566",
    "courseName": "暑期實習",
    "hours": "2.0",
    "units": "2.0",
    "required": "選修",
    "instructors": "李財福",
    "position": "教室未定",
    "people": "2",
    "maxpeople": "55",
    "time": "",
    "english": "否",
    "remote": "否",
    "href": [
      "107",
      "4",
      "UE291441,09635.01"
    ],
    "note": ""
  },
  {
    "code": "0154",
    "cmp": "建工校區",
    "dgr": "日間部四技",
    "unt": "電子工程系[建工|燕巢校區 ]",
    "className": "四子四乙",
    "foreverID": "222C10566",
    "courseName": "暑期實習",
    "hours": "2.0",
    "units": "2.0",
    "required": "選修",
    "instructors": "李財福",
    "position": "教室未定",
    "people": "2",
    "maxpeople": "55",
    "time": "",
    "english": "否",
    "remote": "否",
    "href": [
      "107",
      "4",
      "UE291441,09635.01"
    ],
    "note": ""
  },
  {
    "code": "0154",
    "cmp": "建工校區",
    "dgr": "日間部四技",
    "unt": "電子工程系[建工|燕巢校區 ]",
    "className": "四子四丙",
    "foreverID": "222C10566",
    "courseName": "暑期實習",
    "hours": "2.0",
    "units": "2.0",
    "required": "選修",
    "instructors": "李財福",
    "position": "教室未定",
    "people": "2",
    "maxpeople": "55",
    "time": "",
    "english": "否",
    "remote": "否",
    "href": [
      "107",
      "4",
      "UE291441,09635.01"
    ],
    "note": ""
  }
]