[
  {
    "code": "1312",
    "cmp": "建工校區",
    "dgr": "碩士在職專班",
    "unt": "土木工程系土木工程與防災科技",
    "className": "碩專土木防災一甲",
    "foreverID": "201H00003",
    "courseName": "專題研討(二)",
    "hours": "2.0",
    "units": "2.0",
    "required": "必修",
    "instructors": "郭文田",
    "position": "土702",
    "people": "33",
    "maxpeople": "60",
    "time": "(三)11-12",
    "english": "否",
    "remote": "否",
    "href": [
      "102",
      "2",
      "UE692711,01680.01"
    ],
    "note": ""
  },
  {
    "code": "1313",
    "cmp": "建工校區",
    "dgr": "碩士在職專班",
    "unt": "土木工程系土木工程與防災科技",
    "className": "碩專土木防災一甲",
    "foreverID": "201H10046",
    "courseName": "結構物腐蝕及防治",
    "hours": "3.0",
    "units": "3.0",
    "required": "選修",
    "instructors": "郭文田",
    "position": "土709",
    "people": "7",
    "maxpeople": "30",
    "time": "(二)11-13",
    "english": "否",
    "remote": "否",
    "href": [
      "102",
      "2",
      "UE692711,04400.01"
    ],
    "note": ""
  },
  {
    "code": "1314",
    "cmp": "建工校區",
    "dgr": "碩士在職專班",
    "unt": "土木工程系土木工程與防災科技",
    "className": "碩專土木防災一甲",
    "foreverID": "201H10037",
    "courseName": "3S技術於防災之應用",
    "hours": "3.0",
    "units": "3.0",
    "required": "選修",
    "instructors": "李良輝",
    "position": "土509",
    "people": "15",
    "maxpeople": "30",
    "time": "(四)11-13",
    "english": "否",
    "remote": "否",
    "href": [
      "102",
      "2",
      "UE692711,04689.01"
    ],
    "note": ""
  },
  {
    "code": "1315",
    "cmp": "建工校區",
    "dgr": "碩士在職專班",
    "unt": "土木工程系土木工程與防災科技",
    "className": "碩專土木防災一甲",
    "foreverID": "201H10013",
    "courseName": "營建工程專案管理",
    "hours": "3.0",
    "units": "3.0",
    "required": "選修",
    "instructors": "王裕仁",
    "position": "土302B",
    "people": "13",
    "maxpeople": "30",
    "time": "(六)5-7",
    "english": "否",
    "remote": "否",
    "href": [
      "102",
      "2",
      "UE692711,04821.01"
    ],
    "note": ""
  },
  {
    "code": "1316",
    "cmp": "建工校區",
    "dgr": "碩士在職專班",
    "unt": "土木工程系土木工程與防災科技",
    "className": "碩專土木防災一甲",
    "foreverID": "201H10043",
    "courseName": "價值分析專論",
    "hours": "3.0",
    "units": "3.0",
    "required": "選修",
    "instructors": "王和源",
    "position": "土509",
    "people": "15",
    "maxpeople": "30",
    "time": "(五)11-13",
    "english": "否",
    "remote": "否",
    "href": [
      "102",
      "2",
      "UE692711,05178.01"
    ],
    "note": ""
  },
  {
    "code": "1317",
    "cmp": "建工校區",
    "dgr": "碩士在職專班",
    "unt": "土木工程系土木工程與防災科技",
    "className": "碩專土木防災一甲",
    "foreverID": "201H10025",
    "courseName": "工程破壞案例分析",
    "hours": "3.0",
    "units": "3.0",
    "required": "選修",
    "instructors": "曾世雄",
    "position": "土709",
    "people": "26",
    "maxpeople": "30",
    "time": "(一)11-13",
    "english": "否",
    "remote": "否",
    "href": [
      "102",
      "2",
      "UE692711,05972.01"
    ],
    "note": ""
  },
  {
    "code": "1318",
    "cmp": "建工校區",
    "dgr": "碩士在職專班",
    "unt": "土木工程系土木工程與防災科技",
    "className": "碩專土木防災一甲",
    "foreverID": "201H10066",
    "courseName": "大地防災技術專論",
    "hours": "3.0",
    "units": "3.0",
    "required": "選修",
    "instructors": "蕭達鴻",
    "position": "土509",
    "people": "19",
    "maxpeople": "30",
    "time": "(二)11-13",
    "english": "否",
    "remote": "否",
    "href": [
      "102",
      "2",
      "UE692711,05974.01"
    ],
    "note": ""
  },
  {
    "code": "1319",
    "cmp": "建工校區",
    "dgr": "碩士在職專班",
    "unt": "土木工程系土木工程與防災科技",
    "className": "碩專土木防災一甲",
    "foreverID": "201H10020",
    "courseName": "隔震工程",
    "hours": "3.0",
    "units": "3.0",
    "required": "選修",
    "instructors": "彭生富",
    "position": "土509",
    "people": "6",
    "maxpeople": "30",
    "time": "(日)2-4",
    "english": "否",
    "remote": "",
    "href": [
      "102",
      "2",
      "UE692711,08637.01"
    ],
    "note": ""
  }
]